[
  {
    "id": "00e915fb-cac4-451a-bb90-9eb8907fb7da",
    "grader": "NGC",
    "line1": "2014 BURUNDI G5000F",
    "line2": "JOHN F. KENNEDY",
    "line3": "FIRST DAY OF ISSUE-REV PF",
    "grade": "PF 70",
    "price_jpy": 30000,
    "current_material": "G",
    "numista_material": "NOT_FOUND",
    "numista_name": ""
  },
  {
    "id": "03b137aa-6436-479a-a423-cb984e29c175",
    "grader": "NGC",
    "line1": "2006 P REVERSE PF S$1",
    "line2": "EAGLE 20TH ANNIVERSARY",
    "line3": "",
    "grade": "PF 70",
    "price_jpy": 45000,
    "current_material": "S",
    "numista_material": "NOT_FOUND",
    "numista_name": ""
  },
  {
    "id": "0cbf0c0a-016e-4a6d-b1df-4f15db56362f",
    "grader": "NGC",
    "line1": "1983 G.BRITAIN 1SOV",
    "line2": "",
    "line3": "",
    "grade": "PF 69 ULTRA CAMEO",
    "price_jpy": 240000,
    "current_material": "G",
    "numista_material": "NOT_FOUND",
    "numista_name": ""
  },
  {
    "id": "10132cd2-c88f-4689-a1f4-48d4c1edcc8a",
    "grader": "PCGS",
    "line1": "nd(1917) 50C",
    "line2": "China-Yunan",
    "line3": "Y-479 L&M-863",
    "grade": "AU58",
    "price_jpy": 80000,
    "current_material": "S",
    "numista_material": "NOT_FOUND",
    "numista_name": ""
  },
  {
    "id": "12732fe8-e321-4c84-983d-d05b3ebe1f84",
    "grader": "PCGS",
    "line1": "(1882) M15 1 Rin",
    "line2": "Japan",
    "line3": "JNDA 01-55",
    "grade": "MS65RB",
    "price_jpy": 34500,
    "current_material": "UNKNOWN",
    "numista_material": "NOT_FOUND",
    "numista_name": ""
  },
  {
    "id": "1f431025-a7ca-46bd-855b-d4d827a1f1bc",
    "grader": "NGC",
    "line1": "1915 AUSTRIA DUCAT",
    "line2": "RESTRIKE",
    "line3": "",
    "grade": "MS 68",
    "price_jpy": 128000,
    "current_material": "G",
    "numista_material": "Gold (.986)",
    "numista_name": "1 Ducat - Francis Joseph I"
  },
  {
    "id": "2263da38-73ea-4807-b157-96127912d75b",
    "grader": "NGC",
    "line1": "2022 Cook Is. S$5",
    "line2": "Brilliant Love",
    "line3": "First Releases",
    "grade": "PF 69 ULTRA CAMEO",
    "price_jpy": 33000,
    "current_material": "S",
    "numista_material": "NOT_FOUND",
    "numista_name": ""
  },
  {
    "id": "266cd94e-5289-427d-89bf-71c5edb4e7e8",
    "grader": "NGC",
    "line1": "1847 UN DEC. G.BRITAIN CROWN",
    "line2": "GOTHIC TYPE",
    "line3": "",
    "grade": "PF 61",
    "price_jpy": 2900000,
    "current_material": "S",
    "numista_material": "NOT_FOUND",
    "numista_name": ""
  },
  {
    "id": "2d1df700-920d-416c-851c-0df6e503ee5c",
    "grader": "PCGS",
    "line1": "1840(C or B) Rupee",
    "line2": "India British",
    "line3": "SW-3.33",
    "grade": "MS62",
    "price_jpy": 32500,
    "current_material": "UNKNOWN",
    "numista_material": "NOT_FOUND",
    "numista_name": ""
  },
  {
    "id": "30333968-46aa-49dc-b78e-ab1b357ab6b7",
    "grader": "NGC",
    "line1": "1880 S $1",
    "line2": "",
    "line3": "",
    "grade": "MS 65",
    "price_jpy": 31500,
    "current_material": "S",
    "numista_material": "Silver (.999)",
    "numista_name": "50 Cents - Elizabeth II (4th Portrait - "
  },
  {
    "id": "323d68af-36d6-4e39-84b3-833ef0f9c559",
    "grader": "NGC",
    "line1": "THE QUEEN'S BEASTS",
    "line2": "2017 GREAT BRITAIN 5£2",
    "line3": "THE LION",
    "grade": "PF 70 ULTRA CAMEO",
    "price_jpy": 55800,
    "current_material": "S",
    "numista_material": "NOT_FOUND",
    "numista_name": ""
  },
  {
    "id": "33ad4cbd-3ab0-4a0a-ac5d-c443de3daf53",
    "grader": "PCGS",
    "line1": "(1905) M38 1 Yen",
    "line2": "Japan",
    "line3": "",
    "grade": "MS64",
    "price_jpy": 100100,
    "current_material": "S",
    "numista_material": "NOT_FOUND",
    "numista_name": ""
  },
  {
    "id": "3a8e276f-39d5-455d-906e-b928d5087a5a",
    "grader": "NGC",
    "line1": "1854-DATED FRANCE SILVER",
    "line2": "AMIENS NOTARIES CPMPANY",
    "line3": "(32mm)",
    "grade": "MS 64 DPL",
    "price_jpy": 33500,
    "current_material": "S",
    "numista_material": "NOT_FOUND",
    "numista_name": ""
  },
  {
    "id": "3f3f1768-410c-4c02-9c69-181502875d37",
    "grader": "PCGS",
    "line1": "2002",
    "line2": "France",
    "line3": "Cinderella",
    "grade": "PR68DCAM",
    "price_jpy": 33600,
    "current_material": "UNKNOWN",
    "numista_material": "Bimetallic: silver plated bronze centre in bronze ring",
    "numista_name": "60 Pence - Elizabeth II (Converter)"
  },
  {
    "id": "3f60630d-d6e4-4eb8-aa2e-ed8236eccb5e",
    "grader": "PCGS",
    "line1": "2005 500 Tug",
    "line2": "Mongolia",
    "line3": "Eurasian Eagle Owl",
    "grade": "PR66DCAM",
    "price_jpy": 32557,
    "current_material": "S",
    "numista_material": "NOT_FOUND",
    "numista_name": ""
  },
  {
    "id": "43c7f213-6140-422b-9f92-6051ff26b7d5",
    "grader": "PCGS",
    "line1": "2001 10 Won",
    "line2": "North Korea",
    "line3": "Tortoise-Serpent",
    "grade": "PR 70 DCAM",
    "price_jpy": 32500,
    "current_material": "UNKNOWN",
    "numista_material": "Aluminium",
    "numista_name": "1 Won (Rainbow Lorikeet)"
  },
  {
    "id": "4934ecbd-fe09-44fa-a691-921e2aa19a1c",
    "grader": "PCGS",
    "line1": "(1772-24) 2 Shu",
    "line2": "Japan",
    "line3": "JNDA 09-47 C#13",
    "grade": "MS63",
    "price_jpy": 66670,
    "current_material": "UNKNOWN",
    "numista_material": "NOT_FOUND",
    "numista_name": ""
  },
  {
    "id": "4e4a7dc6-82b9-4fa7-80c8-43e79c8b8d03",
    "grader": "PCGS",
    "line1": "2022 Palau",
    "line2": "Four Leaf Clover Au",
    "line3": "First day of Issue",
    "grade": "PR70DCAM",
    "price_jpy": 61500,
    "current_material": "G",
    "numista_material": "NOT_FOUND",
    "numista_name": ""
  },
  {
    "id": "5385df02-66ba-47ca-8d99-fa413d9a3cc2",
    "grader": "PCGS",
    "line1": "(1986) S61 10 Yen",
    "line2": "Japan",
    "line3": "JNDA 02-9 Later Period",
    "grade": "AU58",
    "price_jpy": 35000,
    "current_material": "UNKNOWN",
    "numista_material": "NOT_FOUND",
    "numista_name": ""
  },
  {
    "id": "55547e73-691a-4dc2-a925-6b655b0f63e6",
    "grader": "PCGS",
    "line1": "ND (1908) CHINA CHIHLI 1 DOLLAR",
    "line2": "L&M-465",
    "line3": "",
    "grade": "GENUINE UNC DETAILS",
    "price_jpy": 100000,
    "current_material": "S",
    "numista_material": "NOT_FOUND",
    "numista_name": ""
  },
  {
    "id": "57958950-5d21-4634-ae38-7f98deb58146",
    "grader": "NGC",
    "line1": "2026 G.Britain $5",
    "line2": "QE II Second Effigy",
    "line3": "First Day of Issue",
    "grade": "PF 70 ULTRA CAMEO",
    "price_jpy": 88000,
    "current_material": "S",
    "numista_material": "NOT_FOUND",
    "numista_name": ""
  },
  {
    "id": "58309b74-26b4-4c77-be04-ea951148b4df",
    "grader": "NGC",
    "line1": "1982 G.BRITAIN 1/2SOV",
    "line2": "",
    "line3": "",
    "grade": "PF 70 ULTRA CAMEO",
    "price_jpy": 198000,
    "current_material": "G",
    "numista_material": "NOT_FOUND",
    "numista_name": ""
  },
  {
    "id": "58a1e55b-bb9f-4b82-af4f-9e43523b93fc",
    "grader": "NGC",
    "line1": "1845 VIII G BRITAIN CROWN",
    "line2": "CINQUEFOIL EDGE",
    "line3": "",
    "grade": "XF DETAILS CLEANED",
    "price_jpy": 44000,
    "current_material": "S",
    "numista_material": "NOT_FOUND",
    "numista_name": ""
  },
  {
    "id": "5a72df0f-0d37-4696-a664-a75a29e5461e",
    "grader": "NGC",
    "line1": "KINGDOM OF MACEDON",
    "line2": "Alexander III, 336-323 BC",
    "line3": "AR Tetradrachm (17.1g)",
    "grade": "obv Heracles rv Zeus hldg. eag",
    "price_jpy": 89800,
    "current_material": "S",
    "numista_material": "NOT_FOUND",
    "numista_name": ""
  },
  {
    "id": "5ead6468-82a1-4e31-9753-64ab7f96438c",
    "grader": "NGC",
    "line1": "1982 G.BRITAIN 1 Sov",
    "line2": "PF 69 ULTRA CAMEO",
    "line3": "",
    "grade": "PF 69 ULTRA CAMEO",
    "price_jpy": 298000,
    "current_material": "G",
    "numista_material": "NOT_FOUND",
    "numista_name": ""
  },
  {
    "id": "6758c771-1e7d-4a76-a295-8f3b63099392",
    "grader": "PCGS",
    "line1": "(1934)二十三 $1",
    "line2": "China, Republic",
    "line3": "LM-110 K-624",
    "grade": "MS 61",
    "price_jpy": 45500,
    "current_material": "UNKNOWN",
    "numista_material": "Copper",
    "numista_name": "1 Yuan (Pattern; \"Junk dollar\"; without "
  },
  {
    "id": "6a20c5e7-d925-4d84-9eaa-6e9838dcbc76",
    "grader": "PCGS",
    "line1": "1994 10 Dim",
    "line2": "Andorra UN Membership",
    "line3": "",
    "grade": "PR69DCAM",
    "price_jpy": 48425,
    "current_material": "S",
    "numista_material": "NOT_FOUND",
    "numista_name": ""
  },
  {
    "id": "72d40115-ed4c-48f8-ab69-f7d2fd3422f3",
    "grader": "NGC",
    "line1": "(1559-67) ITALY 1Z",
    "line2": "VENICE",
    "line3": "GEROLAMO PRIULI",
    "grade": "XF DETAILS",
    "price_jpy": 121000,
    "current_material": "G",
    "numista_material": "NOT_FOUND",
    "numista_name": ""
  },
  {
    "id": "75043d30-c7ac-4581-a662-08b2e862309c",
    "grader": "PCGS",
    "line1": "1908 Medal",
    "line2": "Germany-Empire",
    "line3": "Kaiser-289 Matte",
    "grade": "SP61",
    "price_jpy": 49800,
    "current_material": "UNKNOWN",
    "numista_material": "NOT_FOUND",
    "numista_name": ""
  },
  {
    "id": "75443c8f-f763-476e-9bbd-7ef18f34a4ff",
    "grader": "PCGS",
    "line1": "\"1851\" Crown",
    "line2": "Great Britain",
    "line3": "INA Retro Fantasy Gothic Sn St. George MODEL",
    "grade": "PR66DCAM",
    "price_jpy": 49800,
    "current_material": "UNKNOWN",
    "numista_material": "Copper",
    "numista_name": "1⁄13 Shilling - Victoria"
  },
  {
    "id": "79286858-76bb-49c9-b996-25bc5b615230",
    "grader": "NGC",
    "line1": "M38(1905) JAPAN YEN",
    "line2": "",
    "line3": "",
    "grade": "MS 62",
    "price_jpy": 41055,
    "current_material": "S",
    "numista_material": "NOT_FOUND",
    "numista_name": ""
  },
  {
    "id": "803d55e9-4e1a-4b88-80f4-850c67b4542c",
    "grader": "PCGS",
    "line1": "(1904)甲辰 $1",
    "line2": "China-Kiangnan",
    "line3": "LM-257A Fewer Spines",
    "grade": "MS64",
    "price_jpy": 50000,
    "current_material": "S",
    "numista_material": "NOT_FOUND",
    "numista_name": ""
  },
  {
    "id": "805ea7d4-34fd-4a83-92d0-01d2a57d1083",
    "grader": "PCGS",
    "line1": "1897 (B) Trade$",
    "line2": "Great Britain",
    "line3": "Prid-5",
    "grade": "MS 61",
    "price_jpy": 59500,
    "current_material": "S",
    "numista_material": "Silver (.900)",
    "numista_name": "1 Dollar (British Trade Dollar)"
  },
  {
    "id": "83e3bc53-5503-4941-afdf-08abbc428b8d",
    "grader": "PCGS",
    "line1": "(1885) M18 1 Yen",
    "line2": "Japan",
    "line3": "JNDA 01-10",
    "grade": "MS62",
    "price_jpy": 102001,
    "current_material": "S",
    "numista_material": "NOT_FOUND",
    "numista_name": ""
  },
  {
    "id": "87efe4ba-37ae-43f9-9e36-eb9877614949",
    "grader": "NGC",
    "line1": "1956SO CHILE G100P",
    "line2": "",
    "line3": "",
    "grade": "MS 64",
    "price_jpy": 679800,
    "current_material": "G",
    "numista_material": "NOT_FOUND",
    "numista_name": ""
  },
  {
    "id": "88715fb8-2322-4497-bfa4-ab1b5833f16b",
    "grader": "NGC",
    "line1": "U.S. MINT 225TH ANNIV",
    "line2": "1792-2017 P SILVER MEDAL",
    "line3": "FIRST DAY - PHILADELPHIA",
    "grade": "PF 70 ULTRA CAMEO",
    "price_jpy": 41400,
    "current_material": "S",
    "numista_material": "NOT_FOUND",
    "numista_name": ""
  },
  {
    "id": "8c3bc88a-6183-45f3-8e8d-fc02f39e9fd1",
    "grader": "NGC",
    "line1": "2017 St.Helena G£1",
    "line2": "East India Company",
    "line3": "Imperial One Mohur Design",
    "grade": "PF 70 ULTRA CAMEO",
    "price_jpy": 389000,
    "current_material": "G",
    "numista_material": "NOT_FOUND",
    "numista_name": ""
  },
  {
    "id": "8ec4e75e-e74c-4fc7-9da6-54d3b9540a36",
    "grader": "NGC",
    "line1": "1887 $1",
    "line2": "",
    "line3": "",
    "grade": "MS 64",
    "price_jpy": 31300,
    "current_material": "S",
    "numista_material": "Gold (.9999)",
    "numista_name": "5 Dollars - Elizabeth II (4th Portrait -"
  },
  {
    "id": "934f1440-e904-4549-8376-504df0b9d870",
    "grader": "NGC",
    "line1": "2026 G.Britain S£5",
    "line2": "QE II First Effigy",
    "line3": "First Releases",
    "grade": "PF 70 ULTRA CAMEO",
    "price_jpy": 85700,
    "current_material": "S",
    "numista_material": "NOT_FOUND",
    "numista_name": ""
  },
  {
    "id": "94b450ff-8bb6-4133-a684-a178a0f815b9",
    "grader": "NGC",
    "line1": "1849 G.BRITAIN 2S",
    "line2": "",
    "line3": "",
    "grade": "AU DETAILS CLEANED",
    "price_jpy": 80000,
    "current_material": "S",
    "numista_material": "NOT_FOUND",
    "numista_name": ""
  },
  {
    "id": "959cb7f5-3000-4649-9dde-39161fd17faa",
    "grader": "PCGS",
    "line1": "2017 Canada",
    "line2": "Eyes of the Lynx",
    "line3": "",
    "grade": "PR69DCAM",
    "price_jpy": 89888,
    "current_material": "S",
    "numista_material": "Silver (.9999)",
    "numista_name": "15 Dollars - Elizabeth II (Eyes Of The G"
  },
  {
    "id": "96c5b8eb-53b3-420b-9c83-e7fa29af259b",
    "grader": "PCGS",
    "line1": "(1870) M3 Japan 1 Yen",
    "line2": "PCGS MS63",
    "line3": "Japan",
    "grade": "MS 63",
    "price_jpy": 30566,
    "current_material": "S",
    "numista_material": "NOT_FOUND",
    "numista_name": ""
  },
  {
    "id": "989f184f-7c1b-417c-9f60-10871530d5a6",
    "grader": "NGC",
    "line1": "1881 S $1",
    "line2": "",
    "line3": "",
    "grade": "MS 65",
    "price_jpy": 49800,
    "current_material": "S",
    "numista_material": "Silver (.925) (Ag 925 Cu 75)",
    "numista_name": "25 Pesos (Ibero-American Series - Patacó"
  },
  {
    "id": "98a69801-b0c0-42a7-badd-bfaaa45aa511",
    "grader": "PCGS",
    "line1": "\"1822\" Medal",
    "line2": "France",
    "line3": "Ministry of Trade and Industry Ag Cornst",
    "grade": "SP63",
    "price_jpy": 35100,
    "current_material": "S",
    "numista_material": "Silver (.900)",
    "numista_name": "5 Francs - Louis XVIII (bare bust)"
  },
  {
    "id": "99dd51d4-e1a4-486e-8a2b-ad79c3c71147",
    "grader": "NGC",
    "line1": "1989 CANADA G$5",
    "line2": "MAPLE LEAF",
    "line3": "",
    "grade": "PF 67 ULTRA CAMEO",
    "price_jpy": 119770,
    "current_material": "G",
    "numista_material": "Bronze (98% copper, 1.75% tin, 0.25% zinc)",
    "numista_name": "1 Cent - Elizabeth II (2nd portrait, 12 "
  },
  {
    "id": "9dde1170-35fb-4b20-9514-61c2c47e93fd",
    "grader": "NGC",
    "line1": "(1545-53) ITALY 1Z",
    "line2": "VENICE",
    "line3": "FRANCESCO DONA",
    "grade": "AU DETAILS RIM DAMAGE",
    "price_jpy": 139800,
    "current_material": "G",
    "numista_material": "NOT_FOUND",
    "numista_name": ""
  },
  {
    "id": "9f3be832-6375-496b-b834-685282995db2",
    "grader": "PCGS",
    "line1": "2025 Cook Islands $10",
    "line2": "Reconstruction - Gorilla 2oz Ag",
    "line3": "High Relief First Day of Issue",
    "grade": "PR70DCAM",
    "price_jpy": 79000,
    "current_material": "S",
    "numista_material": "NOT_FOUND",
    "numista_name": ""
  },
  {
    "id": "a9ceb9d5-9754-4c37-a3f4-257ea8b638da",
    "grader": "NGC",
    "line1": "1875 BELGIUM 20F",
    "line2": "POSITION A",
    "line3": "",
    "grade": "MS 63",
    "price_jpy": 244000,
    "current_material": "G",
    "numista_material": "NOT_FOUND",
    "numista_name": ""
  },
  {
    "id": "ac3b77d1-b7a9-43f4-8057-41b23ccf5a85",
    "grader": "NGC",
    "line1": "KINGDOM OF MACEDON",
    "line2": "Alexander III, 336-323 BC",
    "line3": "AR Drachm (4.02g)",
    "grade": "early posthumous issue",
    "price_jpy": 30500,
    "current_material": "S",
    "numista_material": "NOT_FOUND",
    "numista_name": ""
  },
  {
    "id": "acc52731-4a54-4545-bfed-44fcadd15d84",
    "grader": "PCGS",
    "line1": "1924 Medal",
    "line2": "Germany, Weimar Rep.",
    "line3": "Kaiser-451 AE Matte",
    "grade": "SP 65",
    "price_jpy": 59800,
    "current_material": "UNKNOWN",
    "numista_material": "NOT_FOUND",
    "numista_name": ""
  },
  {
    "id": "ad3c7f7f-9dc3-4377-9e9a-e3be752275a4",
    "grader": "NGC",
    "line1": "The Great Engravers",
    "line2": "2020 2oz G.Britain $5",
    "line3": "Three Graces",
    "grade": "PF 70 ULTRA CAMEO",
    "price_jpy": 218000,
    "current_material": "S",
    "numista_material": "NOT_FOUND",
    "numista_name": ""
  },
  {
    "id": "b3c59b1a-c07e-4fc5-a4f2-82cdf7cb9c19",
    "grader": "NGC",
    "line1": "2023 5oz G Britain $15",
    "line2": "Lion and Eagle",
    "line3": "First Day of Issue",
    "grade": "PF 70 ULTRA CAMEO",
    "price_jpy": 42150,
    "current_material": "S",
    "numista_material": "NOT_FOUND",
    "numista_name": ""
  },
  {
    "id": "b94a4677-5c5e-45c1-a31c-e6f8872d71ce",
    "grader": "PCGS",
    "line1": "(1902) M35 1 Yen",
    "line2": "Japan",
    "line3": "",
    "grade": "MS 63",
    "price_jpy": 89000,
    "current_material": "S",
    "numista_material": "NOT_FOUND",
    "numista_name": ""
  },
  {
    "id": "bf0c1100-7f2c-4485-97de-97e373cd1099",
    "grader": "NGC",
    "line1": "1927 COLOMBIA G5P",
    "line2": "MEDELLIN",
    "line3": "",
    "grade": "MS 63",
    "price_jpy": 221000,
    "current_material": "G",
    "numista_material": "NOT_FOUND",
    "numista_name": ""
  },
  {
    "id": "c379c2b3-8cae-4474-aa3f-f049da5e9423",
    "grader": "PCGS",
    "line1": "(1870) M3 1 Yen",
    "line2": "Japan Type I w/Border",
    "line3": "JNDA 01-9",
    "grade": "MS64",
    "price_jpy": 224000,
    "current_material": "S",
    "numista_material": "NOT_FOUND",
    "numista_name": ""
  },
  {
    "id": "c8657d0a-755f-412d-a317-b463ae0a7c2a",
    "grader": "NGC",
    "line1": "THE QUEEN'S BEASTS",
    "line2": "2017 G.BRITAIN 5£2",
    "line3": "THE LION",
    "grade": "PF 70 ULTRA CAMEO",
    "price_jpy": 54000,
    "current_material": "S",
    "numista_material": "NOT_FOUND",
    "numista_name": ""
  },
  {
    "id": "cd45e772-7628-490c-9260-0e7e6b08fd93",
    "grader": "NGC",
    "line1": "1915 AUSTRIA 4D",
    "line2": "RESTRIKE",
    "line3": "",
    "grade": "MS 70",
    "price_jpy": 755000,
    "current_material": "G",
    "numista_material": "NOT_FOUND",
    "numista_name": ""
  },
  {
    "id": "d0ad4024-32a5-4c3d-a7d8-f709488afa3f",
    "grader": "NGC",
    "line1": "1981R SAN MARINO 2S",
    "line2": "WORLD FOOD DAY",
    "line3": "",
    "grade": "MS 66",
    "price_jpy": 185200,
    "current_material": "G",
    "numista_material": "NOT_FOUND",
    "numista_name": ""
  },
  {
    "id": "d126cf27-f2a3-4da6-8d51-64eeccd4ed76",
    "grader": "PCGS",
    "line1": "(1912) 10 Cash",
    "line2": "China-Szechuan",
    "line3": "",
    "grade": "MS63",
    "price_jpy": 50500,
    "current_material": "UNKNOWN",
    "numista_material": "NOT_FOUND",
    "numista_name": ""
  },
  {
    "id": "d7e44476-9347-43a6-b037-6b1dae285d2e",
    "grader": "NGC",
    "line1": "1911 G.BRITAIN 1/2 Sov",
    "line2": "",
    "line3": "",
    "grade": "MS 62",
    "price_jpy": 119880,
    "current_material": "G",
    "numista_material": "NOT_FOUND",
    "numista_name": ""
  },
  {
    "id": "dc270719-5397-4a21-ab4d-ce34be7291f1",
    "grader": "NGC",
    "line1": "2023 2oz G.Britain $£5",
    "line2": "Morgan le Fay",
    "line3": "First Releases",
    "grade": "PF 70 ULTRA CAMEO",
    "price_jpy": 43500,
    "current_material": "S",
    "numista_material": "NOT_FOUND",
    "numista_name": ""
  },
  {
    "id": "e53add55-9602-480e-9769-9f221c13cd3a",
    "grader": "NGC",
    "line1": "1993 G.BRITAIN S£5",
    "line2": "40TH ANNIVERSARY OF REIGN",
    "line3": "",
    "grade": "PF 69 ULTRA CAMEO",
    "price_jpy": 37000,
    "current_material": "S",
    "numista_material": "NOT_FOUND",
    "numista_name": ""
  },
  {
    "id": "e8ab406f-b08b-40df-8d31-6f6fb9011fdb",
    "grader": "NGC",
    "line1": "1944 ROMANIA G20L",
    "line2": "L-51",
    "line3": "",
    "grade": "MS 63",
    "price_jpy": 166000,
    "current_material": "G",
    "numista_material": "NOT_FOUND",
    "numista_name": ""
  },
  {
    "id": "eb624c45-0cf4-4941-bd04-225e32b414dc",
    "grader": "NGC",
    "line1": "1887 G.BRITAIN 4S",
    "line2": "ARABIC 1 IN DATE",
    "line3": "",
    "grade": "MS 62",
    "price_jpy": 47500,
    "current_material": "S",
    "numista_material": "NOT_FOUND",
    "numista_name": ""
  },
  {
    "id": "ed0f72a3-5242-4b4b-996d-ad3eec272253",
    "grader": "PCGS",
    "line1": "1921",
    "line2": "PCGS VF35",
    "line3": "High Relief, Peace",
    "grade": "VF35",
    "price_jpy": 39800,
    "current_material": "S",
    "numista_material": "NOT_FOUND",
    "numista_name": ""
  },
  {
    "id": "ee18e488-3a60-4876-ae63-2705bcb62193",
    "grader": "NGC",
    "line1": "2017 GILT MONGOLIA 5500T",
    "line2": "DEER",
    "line3": "EARLY RELEASES",
    "grade": "MS 70",
    "price_jpy": 50000,
    "current_material": "G",
    "numista_material": "NOT_FOUND",
    "numista_name": ""
  },
  {
    "id": "f12d3c91-d265-4ea2-a97c-574924241f93",
    "grader": "NGC",
    "line1": "2023 Niue S$2",
    "line2": "Yu-Gi-Oh!",
    "line3": "Dark Magician Girl",
    "grade": "MS 69",
    "price_jpy": 65000,
    "current_material": "S",
    "numista_material": "Silver (.999)",
    "numista_name": "2 Dollars - Charles III (Exodia: 4/5)"
  },
  {
    "id": "f22df682-ec48-44de-8788-21e57abae875",
    "grader": "PCGS",
    "line1": "2014",
    "line2": "Silver Eagle",
    "line3": "Direct from U.S. Mint Sealed Box",
    "grade": "MS70",
    "price_jpy": 33900,
    "current_material": "S",
    "numista_material": "Silver (.999)",
    "numista_name": "1 Dollar - Elizabeth II (4th Portrait - "
  },
  {
    "id": "f27daebc-b620-49d1-8931-9ebbd6e13475",
    "grader": "PCGS",
    "line1": "nd(1869) Salung",
    "line2": "Thailand",
    "line3": "Y-29",
    "grade": "AU55",
    "price_jpy": 53000,
    "current_material": "UNKNOWN",
    "numista_material": "NOT_FOUND",
    "numista_name": ""
  },
  {
    "id": "f9d1ac37-f3e8-46bc-9eb1-b91dddc28a42",
    "grader": "NGC",
    "line1": "1914 G.BRITAIN 1/2SOV",
    "line2": "",
    "line3": "",
    "grade": "MS 63",
    "price_jpy": 110880,
    "current_material": "G",
    "numista_material": "NOT_FOUND",
    "numista_name": ""
  },
  {
    "id": "fad20aea-9243-4446-b725-150e2b4ee0a6",
    "grader": "NGC",
    "line1": "2023 G.Britain 5£2",
    "line2": "Bull of Clarence",
    "line3": "",
    "grade": "REVERSE PF 70",
    "price_jpy": 74000,
    "current_material": "S",
    "numista_material": "NOT_FOUND",
    "numista_name": ""
  },
  {
    "id": "fccf6c96-89bf-4e2d-8292-6162f820f2e3",
    "grader": "NGC",
    "line1": "1887 G.BRITAIN 1/2C",
    "line2": "JUBILEE HEAD",
    "line3": "",
    "grade": "MS 63+",
    "price_jpy": 51430,
    "current_material": "UNKNOWN",
    "numista_material": "NOT_FOUND",
    "numista_name": ""
  }
]